adafruit_pcf8574.py
adafruit_circuitpython_pcf8574-1.0.15.dist-info/licenses/LICENSE
adafruit_circuitpython_pcf8574-1.0.15.dist-info/METADATA
adafruit_circuitpython_pcf8574-1.0.15.dist-info/WHEEL
adafruit_circuitpython_pcf8574-1.0.15.dist-info/top_level.txt
adafruit_circuitpython_pcf8574-1.0.15.dist-info/RECORD
